qwif/__init__.py
qwif/cli.py
qwif/contents.py
qwif-0.0.5.dist-info/LICENSE
qwif-0.0.5.dist-info/METADATA
qwif-0.0.5.dist-info/WHEEL
qwif-0.0.5.dist-info/entry_points.txt
qwif-0.0.5.dist-info/top_level.txt
qwif-0.0.5.dist-info/RECORD
