Metadata-Version: 2.1
Name: qwif
Version: 0.0.5
Summary: Generate QR code for WIFI and more.
Home-page: https://gitlab.com/iwaseatenbyagrue/qwif
Author: iwaseatenbyagrue
Author-email: iwaseatenbyagrue@gmail.com
License: BSD-3-Clause
Keywords: cli,qrcode
Platform: UNKNOWN
Classifier: License :: OSI Approved :: BSD License
Classifier: Programming Language :: Python :: 3
Classifier: Programming Language :: Python :: 3.8
Requires-Python: >=3.8
Requires-Dist: qrcode[pil]
Provides-Extra: test
Requires-Dist: tox ; extra == 'test'
Requires-Dist: pytest ; extra == 'test'
Requires-Dist: pytest-cov ; extra == 'test'
Requires-Dist: pytest-pep8 ; extra == 'test'
